{
    "status": "success",
    "category": "tech",
    "count": 2,
    "last_updated": "2026-05-30T16:36:32+00:00",
    "data": [
        {
            "id": "f3bb96a0bdf62fec7557b3e3a3038ddd",
            "url": "https://www.aajtak.in/uttar-pradesh/story/chirag-tyagi-para-athlete-death-ghaziabad-sai-upvan-police-investigation-postmortem-ntc-agkp-rpti-2566094-2026-05-30",
            "source": "Aaj Tak",
            "title": "यूपी: गाजियाबाद में नेशनल पैरा एथलीट चिराग त्यागी की संदिग्ध मौत... साईं उपवन में मिला शव, पीठ पर घाव",
            "description": "राष्ट्रीय पैरा एथलीट चिराग त्यागी की संदिग्ध परिस्थितियों में मौत का मामला सामने आया है. उनका शव गाजियाबाद के कोतवाली थाना क्षेत्र स्थित साईं उपवन इलाके में बरामद किया गया.",
            "full_text": "MumbaiTak\n                                                                        BT Bazaar\n                                                                        Cosmopolitan\n                                                                        Harper&#039;s Bazaar\n                                                                        Northeast\n                                                                        Brides Today\n                                                                        Reader’s Digest\n                                                                        Astro Tak\n                                                \n                    \n                    \n \n\n                \n                            \n            \n            \n                \n                    Sign In\n                \n                \n                    \n                \n            \n        \n    \n  \n\n\n\n(function(){\nlet  restG = document.querySelector(\".rest_arrow\");\nlet ulVisible = document.querySelector(\".gMenuOpen\"); \n\nrestG.addEventListener(\"click\", function(e){\n    ulVisible.classList.toggle(\"openGnav\");\n    e.stopPropagation();\n    restG.classList.toggle(\"rrArrow\");\n    \n    if(!ulVisible.classList.contains(\"openGnav\")){\n        ulVisible.classList.add(\"globBack\");\n}else{\n    ulVisible.classList.remove(\"globBack\");\n};\n\nif(!restG.classList.contains(\"rrArrow\")){\n    restG.classList.add(\"r360\");\n}else{\n    restG.classList.remove(\"r360\");\n};\n\n     });\n\n     ulVisible.addEventListener(\"click\", function(e){\n    e.stopPropagation();\n      });\n \nwindow.addEventListener(\"click\", function(){\n    if(ulVisible.classList.contains(\"openGnav\")){\n        ulVisible.classList.remove(\"openGnav\");\n        ulVisible.classList.add(\"globBack\");\n        restG.classList.add(\"r360\");\n};\nif(restG.classList.contains(\"rrArrow\")){\n    restG.classList.remove(\"rrArrow\");\n};\n\n}); \n})();\n\n\n\nconst slider = document.querySelector(\".top-hed-menu ul\");\nlet isDown = false;\nlet startX;\nlet scrollLeft;\nslider.addEventListener(\"mousedown\", (e) => {\n    isDown = true;\n    slider.classList.add(\"active\");\n    startX = e.pageX - slider.offsetLeft;\n    scrollLeft = slider.scrollLeft;\n});\nslider.addEventListener(\"mouseleave\", () => {\n    isDown = false;\n    slider.classList.remove(\"active\");\n});\nslider.addEventListener(\"mouseup\", () => {\n    isDown = false;\n    slider.classList.remove(\"active\");\n});\nslider.addEventListener(\"mousemove\", (e) => {\n    if (!isDown) return;\n    e.preventDefault();\n    const x = e.pageX - slider.offsetLeft;\n    const walk = (x - startX) * 3;\n    slider.scrollLeft = scrollLeft - walk;\n});\nlet sso_login_btn = document.querySelectorAll(\".ssoSignIn\");\nsso_login_btn.forEach(function(elem) {elem.addEventListener('click', () => {\n    window.location.href = `https://auth.indiatoday.in/saml_login/other/${btoa(window.location.href+\"#ssologin=1\")}`;\n});\n});\n\n\n    &nbsp;          .a { fill: #fff; stroke: #fff; line-height: 30px; }          \n    \n                \n        \n            try{\n                if(atViewPort == \"mobile\"){\n                document.querySelector(\".desktop-logo\").setAttribute('loading',\"lazy\");\n                }\n            }catch(e){\n                console.log(document.querySelector(\".desktop-logo\"));\n            }\n        \n        \n    \n               Sign In         Edition    IN       US           होम      ई-पेपर      भारत        देश  दिल्ली  उत्तर प्रदेश  मध्य प्रदेश  राजस्थान  बिहार  पंजाब  हरियाणा  पश्चिम बंगाल  ओडिशा  हिमाचल प्रदेश  महाराष्ट्र  झारखंड  उत्तराखंड  छत्तीसगढ़  गुजरात  जम्मू कश्मीर  कर्नाटक  तेलंगाना                 मनोरंजन        लेटेस्ट न्यूज  बिग बॉस  साउथ सिनेमा  भोजपुरी  वीडियो  टीवी  वेब स्टोरी  फिल्म रिव्यू                 धर्म        लेटेस्ट  राशिफल  टैरो राशिफल  लव राशिफल  आर्थिक राशिफल  करियर राशिफल  स्वप्न शास्त्र  वीडियो  चाणक्य नीति  वास्तु टिप्स  पर्व-त्यौहार  आरती संग्रह  चालीसा  व्रत कथा                 खेल        खेल न्यूज  IPL  विजुअल स्टोरी  वीडियो  आगामी मैच                 लाइफस्टाइल                                वेब स्टोरी      वीडियो      बिजनेस          बजट  बिजनेस न्यूज  रियल एस्टेट  वेब स्टोरी  स्टॉक अपडेट्स  हॉट स्टॉक  क्रिप्टो  गोल्ड-सिल्वर रेट  पेट्रोल-डीजल रेट  CNG रेट  इनकम टैक्स कैलकुलेटर         AI          AI Sana  अन्य AI एंकर्स  AI की पाठशाला         इन्फ़ॉर्मेशन      विश्व      जुर्म      टेक्नोलॉजी          टेक न्यूज  वेब स्टोरीज  वीडियो  कंज्यूमर इलेक्ट्रॉनिक्स  टिप्स-ट्रिक्स  टेक डील्स  रिव्यूज         पिछले चुनाव          बंगाल चुनाव  बंगाल विजेता  असम चुनाव  असम विजेता  केरल चुनाव  केरल विजेता  तमिलनाडु चुनाव  तमिलनाडु विजेता  पुदुचेरी चुनाव  पुदुचेरी विजेता  बिहार चुनाव  बिहार विजेता  दिल्ली चुनाव  दिल्ली विजेता  महाराष्ट्र चुनाव  महाराष्ट्र विजेता  झारखंड चुनाव  झारखंड विजेता  जम्मू-कश्मीर चुनाव  J&amp;K विजेता  हरियाणा चुनाव  हरियाणा विजेता  लोकसभा चुनाव  लोकसभा विजेता  अरुणाचल प्रदेश चुनाव  अरुणाचल प्रदेश विजेता  सिक्किम चुनाव  सिक्किम विजेता  आंध्र प्रदेश चुनाव  आंध्र प्रदेश विजेता  ओडिशा चुनाव  ओडिशा विजेता         सैर-सपाटा      एजुकेशन          इतिहास में आज  बोर्ड रिजल्ट  सक्सेस स्टोरी  एजुकेशन न्यूज  जॉब्स एंड करियर  नॉलेज  पर्सनैलिटी डेवलपमेंट  विजुअल स्टोरी         डिफेंस न्यूज      कला-संस्कृति      Explained      कार्यक्रम      साइंस न्यूज़      फुल कवरेज      इन्टरैक्टिव      ऑटो      ट्रेंडिंग      फैक्ट चेक      क्विज़      हेल्थ      कृषि समाचार      लीगल न्यूज़      फोटो      आपका पेज      पेट्रोल-डीजल      मौसम      साहित्य      एंकर्स      अर्काइव      गेम्स      বাংলা      रेट कार्ड      निवेशक (Investor)                .a { fill: #fff; stroke: #fff; line-height: 30px; }          X    Edition     IN        US                  =                                   NOTIFICATIONS &nbsp;    30th May                                                         .secarch-cross .st0{fill:#5E769E;}                                 Hindi    English            \nfunction isTouchSupprt() {\n    var supportsTouch = false;\n    if ('ontouchstart' in window)\n        supportsTouch = true;\n    else if (window.navigator.msPointerEnabled)\n        supportsTouch = true;\n    else if ('ontouchstart' in document.documentElement)\n        supportsTouch = true;\n    return supportsTouch;\n}\n(function (){\n    if(!isTouchSupprt()){\n        const nav_sub_child = document.querySelectorAll('.child-dropdown');\n        nav_sub_child.forEach(element => {\n            element.addEventListener(\"mouseenter\", (e)=>{e.target.querySelector('.secondlevel-dropdown').style.display= \"block\";}, {passive: true}, true);\n            element.addEventListener(\"mouseleave\", (e)=>{e.target.querySelector('.secondlevel-dropdown').style.display= \"none\";}, {passive: true});\n        });\n    }\n})();\n\n    const threeDotsNav = document.querySelector(\"#threeDotsNav\");\n    const ShowMutiNav = document.querySelector(\"#mutiNav\");\n    const hideNav = document.querySelector(\"#crossNav\");\n\n\n    threeDotsNav.addEventListener(\"click\", () => {\n        slideToggle();\n        hideNav.style.display = \"block\"\n    });\n\n    hideNav.addEventListener(\"click\", () => {\n    slideToggle();\n    });\n\n\n    ShowMutiNav.addEventListener(\"click\", (e) => {\n        e.stopPropagation();\n    });\n\n    threeDotsNav.addEventListener(\"click\", (e) => {\n        e.stopPropagation();\n    });\n    hideNav.addEventListener(\"click\", (e) => {\n        e.stopPropagation();\n    });\n\n    var slideOpen = false;\n    window.addEventListener(\"click\", () => {\n        if (slideOpen == true) {\n            slideToggle();\n\n        };\n    });\n\n\nconst humburgerMenU = document.querySelector(\".humburgerMenU\");\nconst dotOpenNav = document.querySelector(\".dotOpenNav\");\nconst body = document.querySelector(\"body\");\nconst shadowClass = document.querySelector(\".shadow_class\");\nconst atMDt = document.querySelector(\".atM_dt\");\nconst mobMee = document.querySelector(\".mobMee\");\nconst close = document.querySelector(\".btnclose\");\n\nconst gMenuOpenN = document.querySelector(\".gMenuOpen\");\nconst restArrowW = document.querySelector(\".rest_arrow\");\n\nhumburgerMenU.addEventListener('click', function(e){\n    dotOpenNav.classList.toggle(\"openNavN\");\n    atMDt.classList.toggle(\"menu-at-wrapper\");\n  body.classList.add(\"bgShadowHg\");\n    e.stopPropagation();\n\n    if(gMenuOpenN.classList.contains(\"openGnav\")){\n        gMenuOpenN.classList.remove(\"openGnav\");\n    }\n    if(restArrowW.classList.contains(\"rrArrow\")){\n        restArrowW.classList.remove(\"rrArrow\");\n    }\n});\n\natMDt.addEventListener('click', function(){\n    dotOpenNav.classList.remove(\"openNavN\");\n    this.classList.remove(\"menu-at-wrapper\");\n    body.classList.remove(\"bgShadowHg\");\n\n});\n\nmobMee.addEventListener('click', function(){\n    this.classList.remove(\"menuMobbg\");\n\n});\n\nclose.addEventListener('click', function(e){\n    atMDt.classList.remove(\"menu-at-wrapper\");\n    dotOpenNav.classList.remove(\"openNavN\");\n    body.classList.remove(\"bgShadowHg\");\n    e.stopPropagation();\n});\n\n    function getHeight(el) {\n        var el_style = window.getComputedStyle(el),\n            el_display = el_style.display,\n            el_position = el_style.position,\n            el_visibility = el_style.visibility,\n            el_max_height = el_style.maxHeight.replace('px', '').replace('%', ''),\n\n            wanted_height = 0;\n\n        if (el_display !== 'none' && el_max_height !== '0') {\n            return el.offsetHeight;\n        }\n        el.style.position = 'absolute';\n        el.style.visibility = 'hidden';\n        el.style.display = 'block';\n\n        wanted_height = el.offsetHeight;\n        el.style.display = el_display;\n        el.style.position = el_position;\n        el.style.visibility = el_visibility;\n        return wanted_height;\n    }\n\n    var heightChecked = false;\n    var initHeight = 0;\n    var intval = null;\n\n    function slideToggle() {\n        window.clearInterval(intval);\n        var mdiv = document.getElementById(\"mutiNav\");\n        if (!heightChecked) {\n            initHeight = getHeight(mdiv);\n            heightChecked = true;\n        }\n        if (slideOpen) {\n            var h = initHeight;\n            slideOpen = false;\n            intval = setInterval(function () {\n                h -= 7;\n                mdiv.style.height = h + 'px';\n                mdiv.style.overflow = \"hidden\";\n\n                if (h = initHeight) {\n                    mdiv.style.height = initHeight + 'px';\n                    window.clearInterval(intval);\n                    mdiv.style.overflow = \"visible\";\n                }\n            }, 1);\n        }\n    }\n\n    var closerCheck = function(){\n        return function (){\n            let groupNavAdd = document.querySelector(\".groupNav\");\n            let dynmicCount = \"7\";\n            let deductCount = \"3\";\n            for ( let ipadCount = 0; ipadCount < deductCount; ipadCount++ ) {\n                let count = dynmicCount - ipadCount;\n                lastLi = document.querySelector(\"ul.at-menu li.navNAVLI:nth-child(\"+count+\")\");\n                if(lastLi != null){\n                    groupNavAdd.prepend(lastLi);\n                }\n            }\n        }\n    };\n\n    var check  = closerCheck();\n    window.addEventListener(\"resize\", function1);\n    function function1() {\n        if (window.innerWidth >= 920 && window.innerWidth {\n        el.addEventListener('click', function(e){\n            e.stopPropagation();\n            this.classList.toggle(\"cd-open\");\n            $(\".notification\").stop().slideUp(500);\n            $(\".notification-at\").removeClass(\"bellActive\");\n        });\n    });\n\n    body_for_us_DD.addEventListener('click', function(){\n        cd_item.forEach(el =>{\n            el.classList.remove(\"cd-open\");\n        });\n    });\n        \n    let sso_login_btn_mob = document.querySelector(\".mob-signIn .ssoSignIn\");\n    sso_login_btn_mob.addEventListener('touchstart', () => {\n        window.location.href = `https://auth.indiatoday.in/saml_login/other/${btoa(window.location.href+\"#ssologin=1\")}`;\n    },{passive: true});\n\n      @media (max-width: 767px) {.livetv-nav-sec ul li:nth-child(2) img,.livetv-nav-sec ul li:nth-child(3) img {height: 45px;}} .z-story-detail .tbl-read-more-box {z-index: 9 !important;}     \n\n       Hindi News     उत्तर प्रदेश                    Feedback\n\nFAV US ON                                                फेसबुक     टि्वटर कैंसिल      बुकमार्क  Follow us    फेसबुक     टि्वटर कैंसिल   \n        \n        \n                \n            \n                                \n                            \n                                                                \n                        \n                \n            उत्तर प्रदेश के गाजियाबाद में एक नेशनल पैरा एथलीट की लाश मिली है. पुलिस को रात 7 बजे इसकी खबर मिली. पीठ पर एक छेद मिला है. गोली लगी है या किसी और चीज से चोट. यह पोस्टमॉर्टम के बाद ही पता चलेगा.\n\nगाजियाबाद के कोतवाली थाना इलाके में साईं उपवन में नेशनल पैरा एथलीट चिराग त्यागी की लाश मिली है. चिराग दिल्ली के एक हॉस्टल में रहता था. सुबह वो वहां से अपने गांव बसंतपुर सत्थली मुरादनगर के लिए निकला था. लेकिन वो घर नहीं पहुंचा. उसकी लाश साईं उपवन में मिली.\n\nकोतवाली के SHO सचिन कुमार ने बताया कि चिराग की पीठ पर एक छेद है. अभी यह साफ नहीं है कि यह छेद गोली से हुआ है या किसी और चीज से. पोस्टमॉर्टम के बाद ही सच्चाई सामने आएगी. चिराग के परिवार को खबर दे दी गई है. लाश को पोस्टमॉर्टम के लिए भेजा जा रहा है.\n\nयह खबर अपडेट की जा रही है.\n\n.goToTop{width: 50px;height: 50px;  background: #d71821;-moz-border-radius: 50px;-webkit-border-radius: 50px;border-radius: 50px; -webkit-box-shadow: 3px 3px 5px 0 rgba(0,0,0,.5);-moz-box-shadow: 3px 3px 5px 0 rgba(0,0,0,.5); box-shadow: 3px 3px 5px 0 rgba(0,0,0,.5); cursor: pointer;display: inline-block;  position: fixed;bottom: 170px; right:20px;z-index: 310;transform: scale(0);float:right; -webkit-transition: all 0.3s linear; -moz-transition: all 0.3s ease; -ms-transition: all 0.3s ease; -o-transition: all 0.3s ease; transition: all 0.3s ease; }.goToTop.showGototop { transform: scale(1);} \r\n.goToTop:hover{ background:#bf3c08;transition: all 0.3s ease;}\r\n.goToTopIcon{margin: auto;  left: 1px;  right: 0;  top: 0px; border: 0;  bottom: 0;  position: absolute; height:48px;  width:48px; }\r\n.goToTopIcon .icon-assets-dropdown-arrow-close{ text-align: center; font-size:20px; font-weight: bold; color:#fff; -moz-transition: all 0.3s ease; -ms-transition: all 0.3s ease; -o-transition: all 0.3s ease; transition: all 0.3s ease;}.goToTopIcon .icon-assets-dropdown-arrow-close:before { content: \"\\6e\";}\r\n.goToTopIcon i{color: #fff;font-size: 24px; line-height:23px;} \r\n @media screen and (max-width:767px){.goToTop:hover,.goToTop:active{ background:#f74600;transition: all 0.3s ease;}}\r\n\r\n@media (max-width:800px){.footer-middel-section-main a {line-height: 48px; font-size: 15px; padding: 0px 0; display: block;} .footer-middel-section-main .link-heading {padding-bottom: 10px;}.footer-top-section ul li a {display: inline-block; line-height: 48px;}.fubs_col-first ul li a {display: inline-block; line-height: 48px;}}\r\n\r\n\r\ndocument.addEventListener('DOMContentLoaded', function(event) {var lastScrollTop = 0, delta = 5 , isFooterCssLoded = 0;\r\njQuery(window).scroll(function() {\r\n var nowScrollTop = $(this).scrollTop();\r\nif(Math.abs(lastScrollTop - nowScrollTop) >= delta){\r\n\tif (nowScrollTop > lastScrollTop){\r\n\t\tjQuery('.goToTop').removeClass(\"showGototop\"); \r\n\t} else if(nowScrollTop < 500){\r\n\t\tjQuery('.goToTop').removeClass(\"showGototop\"); \r\n\t}else{\r\n\t\tjQuery('.goToTop').addClass(\"showGototop\");\r\n\t}\r\n\tlastScrollTop = nowScrollTop;\r\n}\r\nif(jQuery(this).scrollTop() >= 500 ){if(isFooterCssLoded == 0){  var $head = $(\"head\"); var linkElement = \"\";$head.append(linkElement);isFooterCssLoded = 1;}}});jQuery(\".goToTop\").click(function () {jQuery(\"body,html\").animate({scrollTop: 0}, 800) });\r\njQuery('.quiz-sso').html('');\r\n});\r\n\r\nif (typeof setCookie === \"undefined\") {\r\nfunction setCookie(o, e = '', t = false) {\r\n    let i = \"\";\r\n    if (t) {\r\n        var n = new Date;\r\n        n.setTime(n.getTime() + 24 * t * 60 * 60 * 1e3),\r\n        i = \"; expires=\" + n.toUTCString()\r\n    }\r\n    document.cookie = o + \"=\" + (e || \"\") + i + \"; path=/\"\r\n}}\r\n\tconst url = window.location.href;\r\n\r\n\t//if (url.includes(\"/india\") || url.includes(\"/religion\")) {\r\n\t\tlet clarityLoaded = false;\r\n\r\n\t\tfunction loadClarity() {\r\n\t\t  if (clarityLoaded) return; // prevent multiple loads\r\n\t\t  clarityLoaded = true;\r\n\r\n\t\t  (function(c,l,a,r,i,t,y){\r\n\t\t\tc[a]=c[a]||function(){(c[a].q=c[a].q||[]).push(arguments)};\r\n\t\t\tt=l.createElement(r);t.async=1;t.src=\"https://www.clarity.ms/tag/\"+i;\r\n\t\t\ty=l.getElementsByTagName(r)[0];y.parentNode.insertBefore(t,y);\r\n\t\t  })(window, document, \"clarity\", \"script\", \"jz3rqqz6w7\");\r\n\t\t}\r\n\t\t\r\n\t\twindow.addEventListener(\"scroll\", loadClarity, { once: true });\r\n\t//}\r\n\n /* cyrillic-ext */ @font-face { font-family: 'Noto Sans'; font-style: normal; font-weight: 400; font-stretch: 100%; font-display: swap; src: url(https://fonts.gstatic.com/s/notosans/v39/o-0bIpQlx3QUlC5A4PNB6Ryti20_6n1iPHjc5aPdu2ui.woff2) format('woff2'); unicode-range: U+0460-052F, U+1C80-1C8A, U+20B4, U+2DE0-2DFF, U+A640-A69F, U+FE2E-FE2F; } /* cyrillic */ @font-face { font-family: 'Noto Sans'; font-style: normal; font-weight: 400; font-stretch: 100%; font-display: swap; src: url(https://fonts.gstatic.com/s/notosans/v39/o-0bIpQlx3QUlC5A4PNB6Ryti20_6n1iPHjc5ardu2ui.woff2) format('woff2'); unicode-range: U+0301, U+0400-045F, U+0490-0491, U+04B0-04B1, U+2116; } /* devanagari */ @font-face { font-family: 'Noto Sans'; font-style: normal; font-weight: 400; font-stretch: 100%; font-display: swap; src: url(https://fonts.gstatic.com/s/notosans/v39/o-0bIpQlx3QUlC5A4PNB6Ryti20_6n1iPHjc5a_du2ui.woff2) format('woff2'); unicode-range: U+0900-097F, U+1CD0-1CF9, U+200C-200D, U+20A8, U+20B9, U+20F0, U+25CC, U+A830-A839, U+A8E0-A8FF, U+11B00-11B09; } /* greek-ext */ @font-face { font-family: 'Noto Sans'; font-style: normal; font-weight: 400; font-stretch: 100%; font-display: swap; src: url(https://fonts.gstatic.com/s/notosans/v39/o-0bIpQlx3QUlC5A4PNB6Ryti20_6n1iPHjc5aLdu2ui.woff2) format('woff2'); unicode-range: U+1F00-1FFF; } /* greek */ @font-face { font-family: 'Noto Sans'; font-style: normal; font-weight: 400; font-stretch: 100%; font-display: swap; src: url(https://fonts.gstatic.com/s/notosans/v39/o-0bIpQlx3QUlC5A4PNB6Ryti20_6n1iPHjc5a3du2ui.woff2) format('woff2'); unicode-range: U+0370-0377, U+037A-037F, U+0384-038A, U+038C, U+038E-03A1, U+03A3-03FF; } /* vietnamese */ @font-face { font-family: 'Noto Sans'; font-style: normal; font-weight: 400; font-stretch: 100%; font-display: swap; src: url(https://fonts.gstatic.com/s/notosans/v39/o-0bIpQlx3QUlC5A4PNB6Ryti20_6n1iPHjc5aHdu2ui.woff2) format('woff2'); unicode-range: U+0102-0103, U+0110-0111, U+0128-0129, U+0168-0169, U+01A0-01A1, U+01AF-01B0, U+0300-0301, U+0303-0304, U+0308-0309, U+0323, U+0329, U+1EA0-1EF9, U+20AB; } /* latin-ext */ @font-face { font-family: 'Noto Sans'; font-style: normal; font-weight: 400; font-stretch: 100%; font-display: swap; src: url(https://fonts.gstatic.com/s/notosans/v39/o-0bIpQlx3QUlC5A4PNB6Ryti20_6n1iPHjc5aDdu2ui.woff2) format('woff2'); unicode-range: U+0100-02BA, U+02BD-02C5, U+02C7-02CC, U+02CE-02D7, U+02DD-02FF, U+0304, U+0308, U+0329, U+1D00-1DBF, U+1E00-1E9F, U+1EF2-1EFF, U+2020, U+20A0-20AB, U+20AD-20C0, U+2113, U+2C60-2C7F, U+A720-A7FF; } /* latin */ @font-face { font-family: 'Noto Sans'; font-style: normal; font-weight: 400; font-stretch: 100%; font-display: swap; src: url(https://fonts.gstatic.com/s/notosans/v39/o-0bIpQlx3QUlC5A4PNB6Ryti20_6n1iPHjc5a7duw.woff2) format('woff2'); unicode-range: U+0000-00FF, U+0131, U+0152-0153, U+02BB-02BC, U+02C6, U+02DA, U+02DC, U+0304, U+0308, U+0329, U+2000-206F, U+20AC, U+2122, U+2191, U+2193, U+2212, U+2215, U+FEFF, U+FFFD; } /* cyrillic-ext */ @font-face { font-family: 'Noto Sans'; font-style: normal; font-weight: 700; font-stretch: 100%; font-display: swap; src: url(https://fonts.gstatic.com/s/notosans/v39/o-0bIpQlx3QUlC5A4PNB6Ryti20_6n1iPHjc5aPdu2ui.woff2) format('woff2'); unicode-range: U+0460-052F, U+1C80-1C8A, U+20B4, U+2DE0-2DFF, U+A640-A69F, U+FE2E-FE2F; } /* cyrillic */ @font-face { font-family: 'Noto Sans'; font-style: normal; font-weight: 700; font-stretch: 100%; font-display: swap; src: url(https://fonts.gstatic.com/s/notosans/v39/o-0bIpQlx3QUlC5A4PNB6Ryti20_6n1iPHjc5ardu2ui.woff2) format('woff2'); unicode-range: U+0301, U+0400-045F, U+0490-0491, U+04B0-04B1, U+2116; } /* devanagari */ @font-face { font-family: 'Noto Sans'; font-style: normal; font-weight: 700; font-stretch: 100%; font-display: swap; src: url(https://fonts.gstatic.com/s/notosans/v39/o-0bIpQlx3QUlC5A4PNB6Ryti20_6n1iPHjc5a_du2ui.woff2) format('woff2'); unicode-range: U+0900-097F, U+1CD0-1CF9, U+200C-200D, U+20A8, U+20B9, U+20F0, U+25CC, U+A830-A839, U+A8E0-A8FF, U+11B00-11B09; } /* greek-ext */ @font-face { font-family: 'Noto Sans'; font-style: normal; font-weight: 700; font-stretch: 100%; font-display: swap; src: url(https://fonts.gstatic.com/s/notosans/v39/o-0bIpQlx3QUlC5A4PNB6Ryti20_6n1iPHjc5aLdu2ui.woff2) format('woff2'); unicode-range: U+1F00-1FFF; } /* greek */ @font-face { font-family: 'Noto Sans'; font-style: normal; font-weight: 700; font-stretch: 100%; font-display: swap; src: url(https://fonts.gstatic.com/s/notosans/v39/o-0bIpQlx3QUlC5A4PNB6Ryti20_6n1iPHjc5a3du2ui.woff2) format('woff2'); unicode-range: U+0370-0377, U+037A-037F, U+0384-038A, U+038C, U+038E-03A1, U+03A3-03FF; } /* vietnamese */ @font-face { font-family: 'Noto Sans'; font-style: normal; font-weight: 700; font-stretch: 100%; font-display: swap; src: url(https://fonts.gstatic.com/s/notosans/v39/o-0bIpQlx3QUlC5A4PNB6Ryti20_6n1iPHjc5aHdu2ui.woff2) format('woff2'); unicode-range: U+0102-0103, U+0110-0111, U+0128-0129, U+0168-0169, U+01A0-01A1, U+01AF-01B0, U+0300-0301, U+0303-0304, U+0308-0309, U+0323, U+0329, U+1EA0-1EF9, U+20AB; } /* latin-ext */ @font-face { font-family: 'Noto Sans'; font-style: normal; font-weight: 700; font-stretch: 100%; font-display: swap; src: url(https://fonts.gstatic.com/s/notosans/v39/o-0bIpQlx3QUlC5A4PNB6Ryti20_6n1iPHjc5aDdu2ui.woff2) format('woff2'); unicode-range: U+0100-02BA, U+02BD-02C5, U+02C7-02CC, U+02CE-02D7, U+02DD-02FF, U+0304, U+0308, U+0329, U+1D00-1DBF, U+1E00-1E9F, U+1EF2-1EFF, U+2020, U+20A0-20AB, U+20AD-20C0, U+2113, U+2C60-2C7F, U+A720-A7FF; } /* latin */ @font-face { font-family: 'Noto Sans'; font-style: normal; font-weight: 700; font-stretch: 100%; font-display: swap; src: url(https://fonts.gstatic.com/s/notosans/v39/o-0bIpQlx3QUlC5A4PNB6Ryti20_6n1iPHjc5a7duw.woff2) format('woff2'); unicode-range: U+0000-00FF, U+0131, U+0152-0153, U+02BB-02BC, U+02C6, U+02DA, U+02DC, U+0304, U+0308, U+0329, U+2000-206F, U+20AC, U+2122, U+2191, U+2193, U+2212, U+2215, U+FEFF, U+FFFD; }                 \n\n\n\n\n\n\n\n\n\n\n\n\n\ndocument.addEventListener(\"DOMContentLoaded\", function () {\n\tconst lazyImages = document.querySelectorAll(\"img.js-lazy-image\");\n\tif (\"IntersectionObserver\" in window) {\n\t\tconst imageObserver = new IntersectionObserver((entries, observer) => {\n\t\t\tentries.forEach((entry) => {\n\t\t\t\tif (entry.isIntersecting) {\n\t\t\t\t\tconst img = entry.target;\n\t\t\t\t\t//console.log(\"Lazy image loaded:\", img.dataset.src);\n\t\t\t\t\timg.src = img.dataset.src; // Set the src attribute to the data-src value\n\t\t\t\t\timg.classList.remove(\"lazy\"); // Remove the lazy class\n\t\t\t\t\tobserver.unobserve(img); // Stop observing the image\n\t\t\t\t}\n\t\t\t});\n\t\t});\n\n\t\tlazyImages.forEach((img) => {\n\t\t\timageObserver.observe(img);\n\t\t});\n\t} else {\n\t\t// Fallback for browsers that don't support Intersection Observer\n\t\tlazyImages.forEach((img) => {\n\t\t\timg.src = img.dataset.src;\n\t\t\timg.classList.remove(\"lazy\");\n\t\t});\n\t}\n});\n\n//only for bigStory and LiveTV Player\nvar both = \"no\";\n\ndocument.addEventListener(\"DOMContentLoaded\", function () {\n    if (typeof atViewPort === \"undefined\") return;\n\n    const wrapper = document.querySelector(\".js-lazy-iframe\");\n    if (!wrapper) return;\n\n    // -------- DESKTOP: LOAD IMMEDIATELY --------\n    if (atViewPort === \"desktop\") {\n\t\tif(both == \"yes\"){\n\t\t\trudrSwitchTab('tb_1', 'content_1');\n\t\t}else{\n\t\t\trudrSwitchTab_order('tb_0', 'content_0');\n\t\t}\n        return;\n    }\n\n    // -------- MOBILE: LOAD ON SCROLL --------\n    if (atViewPort === \"mobile\") {\n        const observer = new IntersectionObserver(entries => {\n            if (entries[0].isIntersecting) {\n                if(both == \"yes\"){\n\t\t\t\t\trudrSwitchTab('tb_1', 'content_1');\n\t\t\t\t}else{\n\t\t\t\t\trudrSwitchTab_order('tb_0', 'content_0');\n\t\t\t\t}\n                observer.disconnect();\n            }\n        }, {\n            rootMargin: \"0px\"\n        });\n\n        observer.observe(wrapper);\n    }\n});\n\n    var _aajtakBKCookie = '__ATBARIKHABAR';\n    var _aajtakBKCookieExp = 1440;\n    var favicon = 'https://akm-img-a-in.tosshub.com/aajtak/resource/img/icons/favicon.ico';\n    /*var favIconAlert = 'https://akm-img-a-in.tosshub.com/aajtak/resource/img/favicon-16x16.png';*/\n    var dataUrl = \"https://www.aajtak.in/ajax/notification\";\n    $(document).click(function (e) {\n        if ($(e.target).closest('#belll').length === 0) {\n            $(\".notification\").slideUp('slow');\n            $(\"#belll\").removeClass(\"bellActive\");\n        }\n    });\n    $(document).ready(function () {\n        checkNotiCookie();\n        var enable_time_interval = \"1\";\n        if(enable_time_interval == '1'){\n            setInterval(function () {\n               checkNotiCookie();\n            }, \"120000\");\n        }\n        $(\"#belll\").on('click', function (event) {\n            event.preventDefault();\n            if (!$(this).hasClass(\"bellActive\")) {\n                /*changeFavicon(favicon);*/\n                var cookieData = getNotiCookie(_aajtakBKCookie);\n                if (cookieData != null) {\n                    getLatestNewsData(cookieData);\n                } else {\n                    getLatestNewsData();\n                }\n                $(this).toggleClass(\"bellActive\");\n            } else {\n                $(this).toggleClass(\"bellActive\");\n            }\n        });\n    });\n    \n    /*function changeFavicon(src) {\n        $('link[rel=\"shortcut icon\"]').attr('href', src)\n    }*/\n    \n    function checkNotiCookie() {\n        var cookieData = getNotiCookie(_aajtakBKCookie);\n        if (cookieData != null) {\n            getAjaxTimestamp(cookieData);\n        } else {\n            getAjaxTimestamp();\n        }\n    }\n    \n    function getNotiCookie(name) {\n        var nameEQ = encodeURIComponent(name) + \"=\";\n        var ca = document.cookie.split(';');\n        for (var i = 0; i < ca.length; i++) {\n            var c = ca[i];\n            while (c.charAt(0) === ' ')\n                c = c.substring(1, c.length);\n            if (c.indexOf(nameEQ) === 0)\n                return decodeURIComponent(c.substring(nameEQ.length, c.length));\n        }\n        return null;\n    }\n    \n    function getAjaxTimestamp(cookieData = '') {\n        $.ajax({\n            url: dataUrl,\n            contentType: \"application/json\",\n            dataType: 'json',\n            callbackParameter: \"c\",\n            cache: true,\n            headers: {'Cache-Control': 'max-age=10'},\n            success: function (data) {\n                let count = 0;\n                $.each(data.latest_notification_count, function( key, value ) {\n                    if (value == cookieData) {\n                        return false;\n                    } else {\n                        return count++;\n                    }\n                });\n                data.latest_count_bell = count;\n                if (cookieData != '') {\n                    setNewsCount(data);             \n                } else {\n                    if (data.unix_datatime) {\n                        setNotiCookie(_aajtakBKCookie, _aajtakBKCookieExp, data.unix_datatime);\n                        setNewsCount(data);\n                        /*changeFavicon(favIconAlert);*/\n                    }\n                }\n            }\n        });\n    }\n    \n    function setNotiCookie(cookieName, cookieTime, data) {\n        var date = new Date();\n        date.setTime(date.getTime() + (cookieTime * 60 * 1000));\n        expires = \"; expires=\" + date.toGMTString();\n        document.cookie = encodeURIComponent(cookieName) + \"=\" + encodeURIComponent(data) + expires + \"; path=/\";\n    }\n    \n    function setNewsCount(data) {\n        if (data.latest_count_bell != 0) {\n            $('.bellCount').text(data.latest_count_bell);\n            $('.bellCount').show();\n            /*changeFavicon(favIconAlert);*/\n        } else {\n            $('.bellCount').hide();\n        }\n    }\n    \n    function getLatestNewsData(cookieData = '') {\n        $.ajax({\n            url: dataUrl,\n            contentType: \"application/json\",\n            dataType: 'json',\n            callbackParameter: \"c\",\n            cache: true,\n            headers: {'Cache-Control': 'max-age=10'},\n            success: function (data) {\n                if (data) {\n                    if(data.unix_datatime != ''){\n                        $('.bellCount').hide();\n                        buildFinalOutPut(data);\n                        setNotiCookie(_aajtakBKCookie, _aajtakBKCookieExp, data.unix_datatime);\n                    }\n                }\n            }\n        });\n    }\n    function buildFinalOutPut(data) {\n        var finalOutPut = '';\n        $(data.latest_notification).each(function (i, item) {\n            finalOutPut = finalOutPut + buildView(item.p);\n        });\n        $('.badiKhabar').html(finalOutPut);\n    }\n    \n    function buildView(item) {\n        var str = '';\n        var seconds = new Date().getTime() / 1000;\n        var currentTime = item.ct;\n        var timeDiff = Math.ceil(seconds - currentTime);\n        var dateTimeNotation = '';\n        var cookieBadiKbrId = getNotiCookie(item.id);\n        var readContent = '';\n        if (cookieBadiKbrId != null) {\n            readContent = 'read';\n        }\n        var contentType = \"Article\";\n        str = str + '';\n        str = str + '';\n        str = str + '';\n        str = str + '';\n        str = str + '';\n        str = str + '' + item.t + '",
            "image": "https://akm-img-a-in.tosshub.com/aajtak/images/story/202605/6a1b0fd9533d8-chirag-tyagi-30270390-16x9.png",
            "published_date": "2026-05-30T21:54:35+05:30",
            "modified_date": "2026-05-30T21:58:10+05:30",
            "keywords": "Chirag Tyagi, National Para Athlete, Ghaziabad, Sai Upvan, Kotwali Police, Uttar Pradesh, Athlete Death, Police Investigation, Postmortem, Muradnagar, Basantpur Sathli, Sports News, Crime News, Delhi Hostel, UP Police, चिराग त्यागी, राष्ट्रीय पैरा एथलीट, गाजियाबाद, साईं उपवन, कोतवाली पुलिस, उत्तर प्रदेश, खिलाड़ी की मौत, पोस्टमार्टम, जांच, मुरादनगर\r\n",
            "category": "tech"
        },
        {
            "id": "d704de7e567b568bc2a10607a96de60b",
            "url": "https://www.aajtak.in/india/maharashtra/story/mumbai-history-sheeter-assaulted-wife-held-hostage-arrested-lclcn-rptc-2566083-2026-05-30",
            "source": "Aaj Tak",
            "title": "4 घंटे तक 'मुर्गा' बनाकर दी यातना, हिस्ट्रीशीटर पति की क्रूरता से दहली महिला, आरोपी गिरफ्तार",
            "description": "मुंबई में 25 वर्षीय हिस्ट्रीशीटर अरबाज सैयद पर पत्नी को घंटों तक पीटने और घर में बंधक बनाकर रखने का आरोप है. पीड़िता किसी तरह बचकर अपने माता-पिता के घर पहुंची, लेकिन आरोपी वहां भी पहुंच गया और दोबारा हमला कर दिया. सूचना मिलने पर पुलिस ने उसे गिरफ्तार कर लिया है. जांच में सामने आया कि आरोपी के खिलाफ पहले से 19 गंभीर आपराधिक मामले दर्ज हैं.",
            "full_text": "MumbaiTak\n                                                                        BT Bazaar\n                                                                        Cosmopolitan\n                                                                        Harper&#039;s Bazaar\n                                                                        Northeast\n                                                                        Brides Today\n                                                                        Reader’s Digest\n                                                                        Astro Tak\n                                                \n                    \n                    \n \n\n                \n                            \n            \n            \n                \n                    Sign In\n                \n                \n                    \n                \n            \n        \n    \n  \n\n\n\n(function(){\nlet  restG = document.querySelector(\".rest_arrow\");\nlet ulVisible = document.querySelector(\".gMenuOpen\"); \n\nrestG.addEventListener(\"click\", function(e){\n    ulVisible.classList.toggle(\"openGnav\");\n    e.stopPropagation();\n    restG.classList.toggle(\"rrArrow\");\n    \n    if(!ulVisible.classList.contains(\"openGnav\")){\n        ulVisible.classList.add(\"globBack\");\n}else{\n    ulVisible.classList.remove(\"globBack\");\n};\n\nif(!restG.classList.contains(\"rrArrow\")){\n    restG.classList.add(\"r360\");\n}else{\n    restG.classList.remove(\"r360\");\n};\n\n     });\n\n     ulVisible.addEventListener(\"click\", function(e){\n    e.stopPropagation();\n      });\n \nwindow.addEventListener(\"click\", function(){\n    if(ulVisible.classList.contains(\"openGnav\")){\n        ulVisible.classList.remove(\"openGnav\");\n        ulVisible.classList.add(\"globBack\");\n        restG.classList.add(\"r360\");\n};\nif(restG.classList.contains(\"rrArrow\")){\n    restG.classList.remove(\"rrArrow\");\n};\n\n}); \n})();\n\n\n\nconst slider = document.querySelector(\".top-hed-menu ul\");\nlet isDown = false;\nlet startX;\nlet scrollLeft;\nslider.addEventListener(\"mousedown\", (e) => {\n    isDown = true;\n    slider.classList.add(\"active\");\n    startX = e.pageX - slider.offsetLeft;\n    scrollLeft = slider.scrollLeft;\n});\nslider.addEventListener(\"mouseleave\", () => {\n    isDown = false;\n    slider.classList.remove(\"active\");\n});\nslider.addEventListener(\"mouseup\", () => {\n    isDown = false;\n    slider.classList.remove(\"active\");\n});\nslider.addEventListener(\"mousemove\", (e) => {\n    if (!isDown) return;\n    e.preventDefault();\n    const x = e.pageX - slider.offsetLeft;\n    const walk = (x - startX) * 3;\n    slider.scrollLeft = scrollLeft - walk;\n});\nlet sso_login_btn = document.querySelectorAll(\".ssoSignIn\");\nsso_login_btn.forEach(function(elem) {elem.addEventListener('click', () => {\n    window.location.href = `https://auth.indiatoday.in/saml_login/other/${btoa(window.location.href+\"#ssologin=1\")}`;\n});\n});\n\n\n    &nbsp;          .a { fill: #fff; stroke: #fff; line-height: 30px; }          \n    \n                \n        \n            try{\n                if(atViewPort == \"mobile\"){\n                document.querySelector(\".desktop-logo\").setAttribute('loading',\"lazy\");\n                }\n            }catch(e){\n                console.log(document.querySelector(\".desktop-logo\"));\n            }\n        \n        \n    \n               Sign In         Edition    IN       US           होम      ई-पेपर      भारत        देश  दिल्ली  उत्तर प्रदेश  मध्य प्रदेश  राजस्थान  बिहार  पंजाब  हरियाणा  पश्चिम बंगाल  ओडिशा  हिमाचल प्रदेश  महाराष्ट्र  झारखंड  उत्तराखंड  छत्तीसगढ़  गुजरात  जम्मू कश्मीर  कर्नाटक  तेलंगाना                 मनोरंजन        लेटेस्ट न्यूज  बिग बॉस  साउथ सिनेमा  भोजपुरी  वीडियो  टीवी  वेब स्टोरी  फिल्म रिव्यू                 धर्म        लेटेस्ट  राशिफल  टैरो राशिफल  लव राशिफल  आर्थिक राशिफल  करियर राशिफल  स्वप्न शास्त्र  वीडियो  चाणक्य नीति  वास्तु टिप्स  पर्व-त्यौहार  आरती संग्रह  चालीसा  व्रत कथा                 खेल        खेल न्यूज  IPL  विजुअल स्टोरी  वीडियो  आगामी मैच                 लाइफस्टाइल                                वेब स्टोरी      वीडियो      बिजनेस          बजट  बिजनेस न्यूज  रियल एस्टेट  वेब स्टोरी  स्टॉक अपडेट्स  हॉट स्टॉक  क्रिप्टो  गोल्ड-सिल्वर रेट  पेट्रोल-डीजल रेट  CNG रेट  इनकम टैक्स कैलकुलेटर         AI          AI Sana  अन्य AI एंकर्स  AI की पाठशाला         इन्फ़ॉर्मेशन      विश्व      जुर्म      टेक्नोलॉजी          टेक न्यूज  वेब स्टोरीज  वीडियो  कंज्यूमर इलेक्ट्रॉनिक्स  टिप्स-ट्रिक्स  टेक डील्स  रिव्यूज         पिछले चुनाव          बंगाल चुनाव  बंगाल विजेता  असम चुनाव  असम विजेता  केरल चुनाव  केरल विजेता  तमिलनाडु चुनाव  तमिलनाडु विजेता  पुदुचेरी चुनाव  पुदुचेरी विजेता  बिहार चुनाव  बिहार विजेता  दिल्ली चुनाव  दिल्ली विजेता  महाराष्ट्र चुनाव  महाराष्ट्र विजेता  झारखंड चुनाव  झारखंड विजेता  जम्मू-कश्मीर चुनाव  J&amp;K विजेता  हरियाणा चुनाव  हरियाणा विजेता  लोकसभा चुनाव  लोकसभा विजेता  अरुणाचल प्रदेश चुनाव  अरुणाचल प्रदेश विजेता  सिक्किम चुनाव  सिक्किम विजेता  आंध्र प्रदेश चुनाव  आंध्र प्रदेश विजेता  ओडिशा चुनाव  ओडिशा विजेता         सैर-सपाटा      एजुकेशन          इतिहास में आज  बोर्ड रिजल्ट  सक्सेस स्टोरी  एजुकेशन न्यूज  जॉब्स एंड करियर  नॉलेज  पर्सनैलिटी डेवलपमेंट  विजुअल स्टोरी         डिफेंस न्यूज      कला-संस्कृति      Explained      कार्यक्रम      साइंस न्यूज़      फुल कवरेज      इन्टरैक्टिव      ऑटो      ट्रेंडिंग      फैक्ट चेक      क्विज़      हेल्थ      कृषि समाचार      लीगल न्यूज़      फोटो      आपका पेज      पेट्रोल-डीजल      मौसम      साहित्य      एंकर्स      अर्काइव      गेम्स      বাংলা      रेट कार्ड      निवेशक (Investor)                .a { fill: #fff; stroke: #fff; line-height: 30px; }          X    Edition     IN        US                  =                                   NOTIFICATIONS &nbsp;    30th May                                                         .secarch-cross .st0{fill:#5E769E;}                                 Hindi    English            \nfunction isTouchSupprt() {\n    var supportsTouch = false;\n    if ('ontouchstart' in window)\n        supportsTouch = true;\n    else if (window.navigator.msPointerEnabled)\n        supportsTouch = true;\n    else if ('ontouchstart' in document.documentElement)\n        supportsTouch = true;\n    return supportsTouch;\n}\n(function (){\n    if(!isTouchSupprt()){\n        const nav_sub_child = document.querySelectorAll('.child-dropdown');\n        nav_sub_child.forEach(element => {\n            element.addEventListener(\"mouseenter\", (e)=>{e.target.querySelector('.secondlevel-dropdown').style.display= \"block\";}, {passive: true}, true);\n            element.addEventListener(\"mouseleave\", (e)=>{e.target.querySelector('.secondlevel-dropdown').style.display= \"none\";}, {passive: true});\n        });\n    }\n})();\n\n    const threeDotsNav = document.querySelector(\"#threeDotsNav\");\n    const ShowMutiNav = document.querySelector(\"#mutiNav\");\n    const hideNav = document.querySelector(\"#crossNav\");\n\n\n    threeDotsNav.addEventListener(\"click\", () => {\n        slideToggle();\n        hideNav.style.display = \"block\"\n    });\n\n    hideNav.addEventListener(\"click\", () => {\n    slideToggle();\n    });\n\n\n    ShowMutiNav.addEventListener(\"click\", (e) => {\n        e.stopPropagation();\n    });\n\n    threeDotsNav.addEventListener(\"click\", (e) => {\n        e.stopPropagation();\n    });\n    hideNav.addEventListener(\"click\", (e) => {\n        e.stopPropagation();\n    });\n\n    var slideOpen = false;\n    window.addEventListener(\"click\", () => {\n        if (slideOpen == true) {\n            slideToggle();\n\n        };\n    });\n\n\nconst humburgerMenU = document.querySelector(\".humburgerMenU\");\nconst dotOpenNav = document.querySelector(\".dotOpenNav\");\nconst body = document.querySelector(\"body\");\nconst shadowClass = document.querySelector(\".shadow_class\");\nconst atMDt = document.querySelector(\".atM_dt\");\nconst mobMee = document.querySelector(\".mobMee\");\nconst close = document.querySelector(\".btnclose\");\n\nconst gMenuOpenN = document.querySelector(\".gMenuOpen\");\nconst restArrowW = document.querySelector(\".rest_arrow\");\n\nhumburgerMenU.addEventListener('click', function(e){\n    dotOpenNav.classList.toggle(\"openNavN\");\n    atMDt.classList.toggle(\"menu-at-wrapper\");\n  body.classList.add(\"bgShadowHg\");\n    e.stopPropagation();\n\n    if(gMenuOpenN.classList.contains(\"openGnav\")){\n        gMenuOpenN.classList.remove(\"openGnav\");\n    }\n    if(restArrowW.classList.contains(\"rrArrow\")){\n        restArrowW.classList.remove(\"rrArrow\");\n    }\n});\n\natMDt.addEventListener('click', function(){\n    dotOpenNav.classList.remove(\"openNavN\");\n    this.classList.remove(\"menu-at-wrapper\");\n    body.classList.remove(\"bgShadowHg\");\n\n});\n\nmobMee.addEventListener('click', function(){\n    this.classList.remove(\"menuMobbg\");\n\n});\n\nclose.addEventListener('click', function(e){\n    atMDt.classList.remove(\"menu-at-wrapper\");\n    dotOpenNav.classList.remove(\"openNavN\");\n    body.classList.remove(\"bgShadowHg\");\n    e.stopPropagation();\n});\n\n    function getHeight(el) {\n        var el_style = window.getComputedStyle(el),\n            el_display = el_style.display,\n            el_position = el_style.position,\n            el_visibility = el_style.visibility,\n            el_max_height = el_style.maxHeight.replace('px', '').replace('%', ''),\n\n            wanted_height = 0;\n\n        if (el_display !== 'none' && el_max_height !== '0') {\n            return el.offsetHeight;\n        }\n        el.style.position = 'absolute';\n        el.style.visibility = 'hidden';\n        el.style.display = 'block';\n\n        wanted_height = el.offsetHeight;\n        el.style.display = el_display;\n        el.style.position = el_position;\n        el.style.visibility = el_visibility;\n        return wanted_height;\n    }\n\n    var heightChecked = false;\n    var initHeight = 0;\n    var intval = null;\n\n    function slideToggle() {\n        window.clearInterval(intval);\n        var mdiv = document.getElementById(\"mutiNav\");\n        if (!heightChecked) {\n            initHeight = getHeight(mdiv);\n            heightChecked = true;\n        }\n        if (slideOpen) {\n            var h = initHeight;\n            slideOpen = false;\n            intval = setInterval(function () {\n                h -= 7;\n                mdiv.style.height = h + 'px';\n                mdiv.style.overflow = \"hidden\";\n\n                if (h = initHeight) {\n                    mdiv.style.height = initHeight + 'px';\n                    window.clearInterval(intval);\n                    mdiv.style.overflow = \"visible\";\n                }\n            }, 1);\n        }\n    }\n\n    var closerCheck = function(){\n        return function (){\n            let groupNavAdd = document.querySelector(\".groupNav\");\n            let dynmicCount = \"7\";\n            let deductCount = \"3\";\n            for ( let ipadCount = 0; ipadCount < deductCount; ipadCount++ ) {\n                let count = dynmicCount - ipadCount;\n                lastLi = document.querySelector(\"ul.at-menu li.navNAVLI:nth-child(\"+count+\")\");\n                if(lastLi != null){\n                    groupNavAdd.prepend(lastLi);\n                }\n            }\n        }\n    };\n\n    var check  = closerCheck();\n    window.addEventListener(\"resize\", function1);\n    function function1() {\n        if (window.innerWidth >= 920 && window.innerWidth {\n        el.addEventListener('click', function(e){\n            e.stopPropagation();\n            this.classList.toggle(\"cd-open\");\n            $(\".notification\").stop().slideUp(500);\n            $(\".notification-at\").removeClass(\"bellActive\");\n        });\n    });\n\n    body_for_us_DD.addEventListener('click', function(){\n        cd_item.forEach(el =>{\n            el.classList.remove(\"cd-open\");\n        });\n    });\n        \n    let sso_login_btn_mob = document.querySelector(\".mob-signIn .ssoSignIn\");\n    sso_login_btn_mob.addEventListener('touchstart', () => {\n        window.location.href = `https://auth.indiatoday.in/saml_login/other/${btoa(window.location.href+\"#ssologin=1\")}`;\n    },{passive: true});\n\n      @media (max-width: 767px) {.livetv-nav-sec ul li:nth-child(2) img,.livetv-nav-sec ul li:nth-child(3) img {height: 45px;}} .z-story-detail .tbl-read-more-box {z-index: 9 !important;}     \n\n       Hindi News    भारत     महाराष्ट्र                    Feedback\n\nFAV US ON                                                फेसबुक     टि्वटर कैंसिल      बुकमार्क  Follow us    फेसबुक     टि्वटर कैंसिल   \n        \n        \n                \n            \n                                \n                            \n                                                                \n                        \n                \n            मुंबई में एक हिस्ट्रीशीटर युवक पर अपनी पत्नी के साथ क्रूरता की सारी हदें पार करने का आरोप लगा है. आरोप है कि उसने घरेलू विवाद के बाद अपनी पत्नी को घंटों तक बेरहमी से पीटा और उसे अपने ही घर में बंधक बनाकर रखा. मामले की शिकायत मिलने के बाद पुलिस ने आरोपी को गिरफ्तार कर लिया है.\n\nपुलिस के अनुसार, आरोपी की पहचान 25 वर्षीय अरबाज सैयद के रूप में हुई है. प्रारंभिक जांच में सामने आया है कि घरेलू विवाद के बाद उसने अपनी पत्नी के साथ मारपीट की. इसके बाद उसने पत्नी को घर के अंदर ही बंद कर दिया और बाहर निकलने नहीं दिया.\n\nयह भी पढ़ें: ISI से जुड़े 9 संदिग्ध गिरफ्तार, दिल्ली-मुंबई में बड़े आतंकी हमलों की साजिश नाकाम\n\nआरोप है कि आरोपी ने अपनी पत्नी को लगभग चार घंटे तक ‘मुर्गा’ की मुद्रा में रहने के लिए मजबूर किया. इस दौरान महिला को लगातार प्रताड़ित किया गया. पीड़िता के अनुसार उसे लंबे समय तक मानसिक और शारीरिक यातना झेलनी पड़ी.\n\nकिसी तरह बचकर पहुंची मायके\n\nपुलिस के मुताबिक, प्रताड़ना के इस दौर के बीच पीड़िता किसी तरह आरोपी के चंगुल से निकलने में सफल रही. अपनी जान बचाने के लिए वह सीधे अपने माता-पिता के घर पहुंच गई.\n\nहालांकि, मामला यहीं नहीं रुका. आरोप है कि अरबाज सैयद अपनी पत्नी का पीछा करते हुए उसके माता-पिता के घर तक पहुंच गया. वहां भी उसने महिला पर दोबारा हमला कर दिया, जिससे परिवार में दहशत फैल गई.\n\nघटना के बाद पीड़िता के परिजनों ने तत्काल पुलिस को सूचना दी. शिकायत मिलने के बाद पुलिस की एक टीम मौके पर पहुंची और आरोपी को हिरासत में ले लिया.\n\nआरोपी पर पहले से दर्ज हैं 19 मामले\n\nजांच के दौरान पुलिस को पता चला कि अरबाज सैयद एक हिस्ट्रीशीटर है. उसके खिलाफ मुंबई के अलग-अलग पुलिस थानों में पहले से 19 गंभीर आपराधिक मामले दर्ज हैं.\n\nपुलिस ने घायल महिला की शिकायत के आधार पर आरोपी के खिलाफ कई गंभीर धाराओं में मामला दर्ज कर लिया है. मामले की जांच जारी है और पुलिस सभी तथ्यों की पड़ताल कर रही है.\n\nफिलहाल आरोपी को गिरफ्तार कर लिया गया है. पुलिस का कहना है कि शिकायत में लगाए गए आरोपों और उपलब्ध साक्ष्यों के आधार पर आगे की कानूनी कार्रवाई की जा रही है.\n\n.goToTop{width: 50px;height: 50px;  background: #d71821;-moz-border-radius: 50px;-webkit-border-radius: 50px;border-radius: 50px; -webkit-box-shadow: 3px 3px 5px 0 rgba(0,0,0,.5);-moz-box-shadow: 3px 3px 5px 0 rgba(0,0,0,.5); box-shadow: 3px 3px 5px 0 rgba(0,0,0,.5); cursor: pointer;display: inline-block;  position: fixed;bottom: 170px; right:20px;z-index: 310;transform: scale(0);float:right; -webkit-transition: all 0.3s linear; -moz-transition: all 0.3s ease; -ms-transition: all 0.3s ease; -o-transition: all 0.3s ease; transition: all 0.3s ease; }.goToTop.showGototop { transform: scale(1);} \r\n.goToTop:hover{ background:#bf3c08;transition: all 0.3s ease;}\r\n.goToTopIcon{margin: auto;  left: 1px;  right: 0;  top: 0px; border: 0;  bottom: 0;  position: absolute; height:48px;  width:48px; }\r\n.goToTopIcon .icon-assets-dropdown-arrow-close{ text-align: center; font-size:20px; font-weight: bold; color:#fff; -moz-transition: all 0.3s ease; -ms-transition: all 0.3s ease; -o-transition: all 0.3s ease; transition: all 0.3s ease;}.goToTopIcon .icon-assets-dropdown-arrow-close:before { content: \"\\6e\";}\r\n.goToTopIcon i{color: #fff;font-size: 24px; line-height:23px;} \r\n @media screen and (max-width:767px){.goToTop:hover,.goToTop:active{ background:#f74600;transition: all 0.3s ease;}}\r\n\r\n@media (max-width:800px){.footer-middel-section-main a {line-height: 48px; font-size: 15px; padding: 0px 0; display: block;} .footer-middel-section-main .link-heading {padding-bottom: 10px;}.footer-top-section ul li a {display: inline-block; line-height: 48px;}.fubs_col-first ul li a {display: inline-block; line-height: 48px;}}\r\n\r\n\r\ndocument.addEventListener('DOMContentLoaded', function(event) {var lastScrollTop = 0, delta = 5 , isFooterCssLoded = 0;\r\njQuery(window).scroll(function() {\r\n var nowScrollTop = $(this).scrollTop();\r\nif(Math.abs(lastScrollTop - nowScrollTop) >= delta){\r\n\tif (nowScrollTop > lastScrollTop){\r\n\t\tjQuery('.goToTop').removeClass(\"showGototop\"); \r\n\t} else if(nowScrollTop < 500){\r\n\t\tjQuery('.goToTop').removeClass(\"showGototop\"); \r\n\t}else{\r\n\t\tjQuery('.goToTop').addClass(\"showGototop\");\r\n\t}\r\n\tlastScrollTop = nowScrollTop;\r\n}\r\nif(jQuery(this).scrollTop() >= 500 ){if(isFooterCssLoded == 0){  var $head = $(\"head\"); var linkElement = \"\";$head.append(linkElement);isFooterCssLoded = 1;}}});jQuery(\".goToTop\").click(function () {jQuery(\"body,html\").animate({scrollTop: 0}, 800) });\r\njQuery('.quiz-sso').html('');\r\n});\r\n\r\nif (typeof setCookie === \"undefined\") {\r\nfunction setCookie(o, e = '', t = false) {\r\n    let i = \"\";\r\n    if (t) {\r\n        var n = new Date;\r\n        n.setTime(n.getTime() + 24 * t * 60 * 60 * 1e3),\r\n        i = \"; expires=\" + n.toUTCString()\r\n    }\r\n    document.cookie = o + \"=\" + (e || \"\") + i + \"; path=/\"\r\n}}\r\n\tconst url = window.location.href;\r\n\r\n\t//if (url.includes(\"/india\") || url.includes(\"/religion\")) {\r\n\t\tlet clarityLoaded = false;\r\n\r\n\t\tfunction loadClarity() {\r\n\t\t  if (clarityLoaded) return; // prevent multiple loads\r\n\t\t  clarityLoaded = true;\r\n\r\n\t\t  (function(c,l,a,r,i,t,y){\r\n\t\t\tc[a]=c[a]||function(){(c[a].q=c[a].q||[]).push(arguments)};\r\n\t\t\tt=l.createElement(r);t.async=1;t.src=\"https://www.clarity.ms/tag/\"+i;\r\n\t\t\ty=l.getElementsByTagName(r)[0];y.parentNode.insertBefore(t,y);\r\n\t\t  })(window, document, \"clarity\", \"script\", \"jz3rqqz6w7\");\r\n\t\t}\r\n\t\t\r\n\t\twindow.addEventListener(\"scroll\", loadClarity, { once: true });\r\n\t//}\r\n\n /* cyrillic-ext */ @font-face { font-family: 'Noto Sans'; font-style: normal; font-weight: 400; font-stretch: 100%; font-display: swap; src: url(https://fonts.gstatic.com/s/notosans/v39/o-0bIpQlx3QUlC5A4PNB6Ryti20_6n1iPHjc5aPdu2ui.woff2) format('woff2'); unicode-range: U+0460-052F, U+1C80-1C8A, U+20B4, U+2DE0-2DFF, U+A640-A69F, U+FE2E-FE2F; } /* cyrillic */ @font-face { font-family: 'Noto Sans'; font-style: normal; font-weight: 400; font-stretch: 100%; font-display: swap; src: url(https://fonts.gstatic.com/s/notosans/v39/o-0bIpQlx3QUlC5A4PNB6Ryti20_6n1iPHjc5ardu2ui.woff2) format('woff2'); unicode-range: U+0301, U+0400-045F, U+0490-0491, U+04B0-04B1, U+2116; } /* devanagari */ @font-face { font-family: 'Noto Sans'; font-style: normal; font-weight: 400; font-stretch: 100%; font-display: swap; src: url(https://fonts.gstatic.com/s/notosans/v39/o-0bIpQlx3QUlC5A4PNB6Ryti20_6n1iPHjc5a_du2ui.woff2) format('woff2'); unicode-range: U+0900-097F, U+1CD0-1CF9, U+200C-200D, U+20A8, U+20B9, U+20F0, U+25CC, U+A830-A839, U+A8E0-A8FF, U+11B00-11B09; } /* greek-ext */ @font-face { font-family: 'Noto Sans'; font-style: normal; font-weight: 400; font-stretch: 100%; font-display: swap; src: url(https://fonts.gstatic.com/s/notosans/v39/o-0bIpQlx3QUlC5A4PNB6Ryti20_6n1iPHjc5aLdu2ui.woff2) format('woff2'); unicode-range: U+1F00-1FFF; } /* greek */ @font-face { font-family: 'Noto Sans'; font-style: normal; font-weight: 400; font-stretch: 100%; font-display: swap; src: url(https://fonts.gstatic.com/s/notosans/v39/o-0bIpQlx3QUlC5A4PNB6Ryti20_6n1iPHjc5a3du2ui.woff2) format('woff2'); unicode-range: U+0370-0377, U+037A-037F, U+0384-038A, U+038C, U+038E-03A1, U+03A3-03FF; } /* vietnamese */ @font-face { font-family: 'Noto Sans'; font-style: normal; font-weight: 400; font-stretch: 100%; font-display: swap; src: url(https://fonts.gstatic.com/s/notosans/v39/o-0bIpQlx3QUlC5A4PNB6Ryti20_6n1iPHjc5aHdu2ui.woff2) format('woff2'); unicode-range: U+0102-0103, U+0110-0111, U+0128-0129, U+0168-0169, U+01A0-01A1, U+01AF-01B0, U+0300-0301, U+0303-0304, U+0308-0309, U+0323, U+0329, U+1EA0-1EF9, U+20AB; } /* latin-ext */ @font-face { font-family: 'Noto Sans'; font-style: normal; font-weight: 400; font-stretch: 100%; font-display: swap; src: url(https://fonts.gstatic.com/s/notosans/v39/o-0bIpQlx3QUlC5A4PNB6Ryti20_6n1iPHjc5aDdu2ui.woff2) format('woff2'); unicode-range: U+0100-02BA, U+02BD-02C5, U+02C7-02CC, U+02CE-02D7, U+02DD-02FF, U+0304, U+0308, U+0329, U+1D00-1DBF, U+1E00-1E9F, U+1EF2-1EFF, U+2020, U+20A0-20AB, U+20AD-20C0, U+2113, U+2C60-2C7F, U+A720-A7FF; } /* latin */ @font-face { font-family: 'Noto Sans'; font-style: normal; font-weight: 400; font-stretch: 100%; font-display: swap; src: url(https://fonts.gstatic.com/s/notosans/v39/o-0bIpQlx3QUlC5A4PNB6Ryti20_6n1iPHjc5a7duw.woff2) format('woff2'); unicode-range: U+0000-00FF, U+0131, U+0152-0153, U+02BB-02BC, U+02C6, U+02DA, U+02DC, U+0304, U+0308, U+0329, U+2000-206F, U+20AC, U+2122, U+2191, U+2193, U+2212, U+2215, U+FEFF, U+FFFD; } /* cyrillic-ext */ @font-face { font-family: 'Noto Sans'; font-style: normal; font-weight: 700; font-stretch: 100%; font-display: swap; src: url(https://fonts.gstatic.com/s/notosans/v39/o-0bIpQlx3QUlC5A4PNB6Ryti20_6n1iPHjc5aPdu2ui.woff2) format('woff2'); unicode-range: U+0460-052F, U+1C80-1C8A, U+20B4, U+2DE0-2DFF, U+A640-A69F, U+FE2E-FE2F; } /* cyrillic */ @font-face { font-family: 'Noto Sans'; font-style: normal; font-weight: 700; font-stretch: 100%; font-display: swap; src: url(https://fonts.gstatic.com/s/notosans/v39/o-0bIpQlx3QUlC5A4PNB6Ryti20_6n1iPHjc5ardu2ui.woff2) format('woff2'); unicode-range: U+0301, U+0400-045F, U+0490-0491, U+04B0-04B1, U+2116; } /* devanagari */ @font-face { font-family: 'Noto Sans'; font-style: normal; font-weight: 700; font-stretch: 100%; font-display: swap; src: url(https://fonts.gstatic.com/s/notosans/v39/o-0bIpQlx3QUlC5A4PNB6Ryti20_6n1iPHjc5a_du2ui.woff2) format('woff2'); unicode-range: U+0900-097F, U+1CD0-1CF9, U+200C-200D, U+20A8, U+20B9, U+20F0, U+25CC, U+A830-A839, U+A8E0-A8FF, U+11B00-11B09; } /* greek-ext */ @font-face { font-family: 'Noto Sans'; font-style: normal; font-weight: 700; font-stretch: 100%; font-display: swap; src: url(https://fonts.gstatic.com/s/notosans/v39/o-0bIpQlx3QUlC5A4PNB6Ryti20_6n1iPHjc5aLdu2ui.woff2) format('woff2'); unicode-range: U+1F00-1FFF; } /* greek */ @font-face { font-family: 'Noto Sans'; font-style: normal; font-weight: 700; font-stretch: 100%; font-display: swap; src: url(https://fonts.gstatic.com/s/notosans/v39/o-0bIpQlx3QUlC5A4PNB6Ryti20_6n1iPHjc5a3du2ui.woff2) format('woff2'); unicode-range: U+0370-0377, U+037A-037F, U+0384-038A, U+038C, U+038E-03A1, U+03A3-03FF; } /* vietnamese */ @font-face { font-family: 'Noto Sans'; font-style: normal; font-weight: 700; font-stretch: 100%; font-display: swap; src: url(https://fonts.gstatic.com/s/notosans/v39/o-0bIpQlx3QUlC5A4PNB6Ryti20_6n1iPHjc5aHdu2ui.woff2) format('woff2'); unicode-range: U+0102-0103, U+0110-0111, U+0128-0129, U+0168-0169, U+01A0-01A1, U+01AF-01B0, U+0300-0301, U+0303-0304, U+0308-0309, U+0323, U+0329, U+1EA0-1EF9, U+20AB; } /* latin-ext */ @font-face { font-family: 'Noto Sans'; font-style: normal; font-weight: 700; font-stretch: 100%; font-display: swap; src: url(https://fonts.gstatic.com/s/notosans/v39/o-0bIpQlx3QUlC5A4PNB6Ryti20_6n1iPHjc5aDdu2ui.woff2) format('woff2'); unicode-range: U+0100-02BA, U+02BD-02C5, U+02C7-02CC, U+02CE-02D7, U+02DD-02FF, U+0304, U+0308, U+0329, U+1D00-1DBF, U+1E00-1E9F, U+1EF2-1EFF, U+2020, U+20A0-20AB, U+20AD-20C0, U+2113, U+2C60-2C7F, U+A720-A7FF; } /* latin */ @font-face { font-family: 'Noto Sans'; font-style: normal; font-weight: 700; font-stretch: 100%; font-display: swap; src: url(https://fonts.gstatic.com/s/notosans/v39/o-0bIpQlx3QUlC5A4PNB6Ryti20_6n1iPHjc5a7duw.woff2) format('woff2'); unicode-range: U+0000-00FF, U+0131, U+0152-0153, U+02BB-02BC, U+02C6, U+02DA, U+02DC, U+0304, U+0308, U+0329, U+2000-206F, U+20AC, U+2122, U+2191, U+2193, U+2212, U+2215, U+FEFF, U+FFFD; }                 \n\n\n\n\n\n\n\n\n\n\n\n\n\ndocument.addEventListener(\"DOMContentLoaded\", function () {\n\tconst lazyImages = document.querySelectorAll(\"img.js-lazy-image\");\n\tif (\"IntersectionObserver\" in window) {\n\t\tconst imageObserver = new IntersectionObserver((entries, observer) => {\n\t\t\tentries.forEach((entry) => {\n\t\t\t\tif (entry.isIntersecting) {\n\t\t\t\t\tconst img = entry.target;\n\t\t\t\t\t//console.log(\"Lazy image loaded:\", img.dataset.src);\n\t\t\t\t\timg.src = img.dataset.src; // Set the src attribute to the data-src value\n\t\t\t\t\timg.classList.remove(\"lazy\"); // Remove the lazy class\n\t\t\t\t\tobserver.unobserve(img); // Stop observing the image\n\t\t\t\t}\n\t\t\t});\n\t\t});\n\n\t\tlazyImages.forEach((img) => {\n\t\t\timageObserver.observe(img);\n\t\t});\n\t} else {\n\t\t// Fallback for browsers that don't support Intersection Observer\n\t\tlazyImages.forEach((img) => {\n\t\t\timg.src = img.dataset.src;\n\t\t\timg.classList.remove(\"lazy\");\n\t\t});\n\t}\n});\n\n//only for bigStory and LiveTV Player\nvar both = \"no\";\n\ndocument.addEventListener(\"DOMContentLoaded\", function () {\n    if (typeof atViewPort === \"undefined\") return;\n\n    const wrapper = document.querySelector(\".js-lazy-iframe\");\n    if (!wrapper) return;\n\n    // -------- DESKTOP: LOAD IMMEDIATELY --------\n    if (atViewPort === \"desktop\") {\n\t\tif(both == \"yes\"){\n\t\t\trudrSwitchTab('tb_1', 'content_1');\n\t\t}else{\n\t\t\trudrSwitchTab_order('tb_0', 'content_0');\n\t\t}\n        return;\n    }\n\n    // -------- MOBILE: LOAD ON SCROLL --------\n    if (atViewPort === \"mobile\") {\n        const observer = new IntersectionObserver(entries => {\n            if (entries[0].isIntersecting) {\n                if(both == \"yes\"){\n\t\t\t\t\trudrSwitchTab('tb_1', 'content_1');\n\t\t\t\t}else{\n\t\t\t\t\trudrSwitchTab_order('tb_0', 'content_0');\n\t\t\t\t}\n                observer.disconnect();\n            }\n        }, {\n            rootMargin: \"0px\"\n        });\n\n        observer.observe(wrapper);\n    }\n});\n\n    var _aajtakBKCookie = '__ATBARIKHABAR';\n    var _aajtakBKCookieExp = 1440;\n    var favicon = 'https://akm-img-a-in.tosshub.com/aajtak/resource/img/icons/favicon.ico';\n    /*var favIconAlert = 'https://akm-img-a-in.tosshub.com/aajtak/resource/img/favicon-16x16.png';*/\n    var dataUrl = \"https://www.aajtak.in/ajax/notification\";\n    $(document).click(function (e) {\n        if ($(e.target).closest('#belll').length === 0) {\n            $(\".notification\").slideUp('slow');\n            $(\"#belll\").removeClass(\"bellActive\");\n        }\n    });\n    $(document).ready(function () {\n        checkNotiCookie();\n        var enable_time_interval = \"1\";\n        if(enable_time_interval == '1'){\n            setInterval(function () {\n               checkNotiCookie();\n            }, \"120000\");\n        }\n        $(\"#belll\").on('click', function (event) {\n            event.preventDefault();\n            if (!$(this).hasClass(\"bellActive\")) {\n                /*changeFavicon(favicon);*/\n                var cookieData = getNotiCookie(_aajtakBKCookie);\n                if (cookieData != null) {\n                    getLatestNewsData(cookieData);\n                } else {\n                    getLatestNewsData();\n                }\n                $(this).toggleClass(\"bellActive\");\n            } else {\n                $(this).toggleClass(\"bellActive\");\n            }\n        });\n    });\n    \n    /*function changeFavicon(src) {\n        $('link[rel=\"shortcut icon\"]').attr('href', src)\n    }*/\n    \n    function checkNotiCookie() {\n        var cookieData = getNotiCookie(_aajtakBKCookie);\n        if (cookieData != null) {\n            getAjaxTimestamp(cookieData);\n        } else {\n            getAjaxTimestamp();\n        }\n    }\n    \n    function getNotiCookie(name) {\n        var nameEQ = encodeURIComponent(name) + \"=\";\n        var ca = document.cookie.split(';');\n        for (var i = 0; i < ca.length; i++) {\n            var c = ca[i];\n            while (c.charAt(0) === ' ')\n                c = c.substring(1, c.length);\n            if (c.indexOf(nameEQ) === 0)\n                return decodeURIComponent(c.substring(nameEQ.length, c.length));\n        }\n        return null;\n    }\n    \n    function getAjaxTimestamp(cookieData = '') {\n        $.ajax({\n            url: dataUrl,\n            contentType: \"application/json\",\n            dataType: 'json',\n            callbackParameter: \"c\",\n            cache: true,\n            headers: {'Cache-Control': 'max-age=10'},\n            success: function (data) {\n                let count = 0;\n                $.each(data.latest_notification_count, function( key, value ) {\n                    if (value == cookieData) {\n                        return false;\n                    } else {\n                        return count++;\n                    }\n                });\n                data.latest_count_bell = count;\n                if (cookieData != '') {\n                    setNewsCount(data);             \n                } else {\n                    if (data.unix_datatime) {\n                        setNotiCookie(_aajtakBKCookie, _aajtakBKCookieExp, data.unix_datatime);\n                        setNewsCount(data);\n                        /*changeFavicon(favIconAlert);*/\n                    }\n                }\n            }\n        });\n    }\n    \n    function setNotiCookie(cookieName, cookieTime, data) {\n        var date = new Date();\n        date.setTime(date.getTime() + (cookieTime * 60 * 1000));\n        expires = \"; expires=\" + date.toGMTString();\n        document.cookie = encodeURIComponent(cookieName) + \"=\" + encodeURIComponent(data) + expires + \"; path=/\";\n    }\n    \n    function setNewsCount(data) {\n        if (data.latest_count_bell != 0) {\n            $('.bellCount').text(data.latest_count_bell);\n            $('.bellCount').show();\n            /*changeFavicon(favIconAlert);*/\n        } else {\n            $('.bellCount').hide();\n        }\n    }\n    \n    function getLatestNewsData(cookieData = '') {\n        $.ajax({\n            url: dataUrl,\n            contentType: \"application/json\",\n            dataType: 'json',\n            callbackParameter: \"c\",\n            cache: true,\n            headers: {'Cache-Control': 'max-age=10'},\n            success: function (data) {\n                if (data) {\n                    if(data.unix_datatime != ''){\n                        $('.bellCount').hide();\n                        buildFinalOutPut(data);\n                        setNotiCookie(_aajtakBKCookie, _aajtakBKCookieExp, data.unix_datatime);\n                    }\n                }\n            }\n        });\n    }\n    function buildFinalOutPut(data) {\n        var finalOutPut = '';\n        $(data.latest_notification).each(function (i, item) {\n            finalOutPut = finalOutPut + buildView(item.p);\n        });\n        $('.badiKhabar').html(finalOutPut);\n    }\n    \n    function buildView(item) {\n        var str = '';\n        var seconds = new Date().getTime() / 1000;\n        var currentTime = item.ct;\n        var timeDiff = Math.ceil(seconds - currentTime);\n        var dateTimeNotation = '';\n        var cookieBadiKbrId = getNotiCookie(item.id);\n        var readContent = '';\n        if (cookieBadiKbrId != null) {\n            readContent = 'read';\n        }\n        var contentType = \"Article\";\n        str = str + '';\n        str = str + '';\n        str = str + '';\n        str = str + '';\n        str = str + '';\n        str = str + '' + item.t + '",
            "image": "https://akm-img-a-in.tosshub.com/aajtak/images/story/202605/6a1b07faaae6c-mumbai-305325152-16x9.jpg",
            "published_date": "2026-05-30T21:26:28+05:30",
            "modified_date": "2026-05-30T21:26:28+05:30",
            "keywords": "मुंबई, अरबाज सैयद, हिस्ट्रीशीटर, पत्नी से मारपीट, घरेलू हिंसा, बंधक बनाना, महिला उत्पीड़न, मुर्गा सजा, मायके में हमला, पुलिस गिरफ्तारी, 19 आपराधिक मामले, घरेलू विवाद, महिला सुरक्षा, मुंबई क्राइम, आरोपी गिरफ्तार, Mumbai, Arbaz Syed, History-sheeter, Assault on wife, Domestic violence, Taking hostage, Harassment of women, 'Murga' punishment, Attack at in-laws' home, Police arrest, 19 criminal cases, Domestic dispute, Women's safety, Mumbai Crime, Accused arrested",
            "category": "tech"
        }
    ]
}